Nvuti_Bot/__init__.py
Nvuti_Bot/browser.py
Nvuti_UDP/__init__.py
Nvuti_UDP/udp.py
nvuti-0.1.dist-info/METADATA
nvuti-0.1.dist-info/WHEEL
nvuti-0.1.dist-info/top_level.txt
nvuti-0.1.dist-info/RECORD
