Metadata-Version: 2.1
Name: nvuti
Version: 0.1
Summary: Package for use NvutiAPI parser
Home-page: http://github.com/DeadRain/NvutiAPI
Author: Prozenq
Author-email: kepera@inbox.ru
License: MIT
Keywords: nvuti
Platform: UNKNOWN
Classifier: Development Status :: 3 - Alpha
Classifier: License :: OSI Approved :: MIT License
Classifier: Programming Language :: Python :: 2.7
Classifier: Topic :: Text Processing :: Linguistic
Requires-Dist: markdown
